openmv/__init__.py
openmv/buffer.py
openmv/camera.py
openmv/cli.py
openmv/constants.py
openmv/crc.py
openmv/exceptions.py
openmv/image.py
openmv/profiler.py
openmv/transport.py
openmv-1.0.6.dist-info/licenses/LICENSE
openmv-1.0.6.dist-info/METADATA
openmv-1.0.6.dist-info/WHEEL
openmv-1.0.6.dist-info/entry_points.txt
openmv-1.0.6.dist-info/top_level.txt
openmv-1.0.6.dist-info/RECORD
