Metadata-Version: 2.4
Name: openmv
Version: 1.0.6
Summary: OpenMV Camera Protocol V2 - Python library and CLI
Author-email: "OpenMV, LLC" <info@openmv.io>
License: MIT
Project-URL: Homepage, https://openmv.io
Project-URL: Documentation, https://docs.openmv.io
Project-URL: Repository, https://github.com/openmv/openmv-python
Project-URL: Issues, https://github.com/openmv/openmv-python/issues
Keywords: openmv,camera,machine-vision,embedded,micropython
Classifier: Development Status :: 4 - Beta
Classifier: Environment :: Console
Classifier: Intended Audience :: Developers
Classifier: License :: OSI Approved :: MIT License
Classifier: Operating System :: OS Independent
Classifier: Programming Language :: Python :: 3
Classifier: Programming Language :: Python :: 3.8
Classifier: Programming Language :: Python :: 3.9
Classifier: Programming Language :: Python :: 3.10
Classifier: Programming Language :: Python :: 3.11
Classifier: Programming Language :: Python :: 3.12
Classifier: Topic :: Scientific/Engineering :: Image Processing
Classifier: Topic :: Software Development :: Embedded Systems
Requires-Python: >=3.8
License-File: LICENSE
Requires-Dist: pyserial>=3.5
Requires-Dist: numpy>=1.20.0
Requires-Dist: pygame>=2.0.0
Requires-Dist: pyelftools
Dynamic: license-file
